MDAnalysisData/CG_fiber.py
MDAnalysisData/PEG_1chain.py
MDAnalysisData/__init__.py
MDAnalysisData/_version.py
MDAnalysisData/adk_equilibrium.py
MDAnalysisData/adk_transitions.py
MDAnalysisData/authors.py
MDAnalysisData/base.py
MDAnalysisData/datasets.py
MDAnalysisData/ifabp_water.py
MDAnalysisData/membrane_peptide.py
MDAnalysisData/nhaa_equilibrium.py
MDAnalysisData/vesicles.py
MDAnalysisData/yiip_equilibrium.py
MDAnalysisData/descr/CG_fiber.rst
MDAnalysisData/descr/PEG_1chain.rst
MDAnalysisData/descr/adk_equilibrium.rst
MDAnalysisData/descr/adk_transitions_DIMS.rst
MDAnalysisData/descr/adk_transitions_FRODA.rst
MDAnalysisData/descr/ifabp_water.rst
MDAnalysisData/descr/membrane_peptide.rst
MDAnalysisData/descr/nhaa_equilibrium.rst
MDAnalysisData/descr/vesicle_lib.rst
MDAnalysisData/descr/yiip_equilibrium.rst
MDAnalysisData/tests/__init__.py
MDAnalysisData/tests/test_base.py
MDAnalysisData/tests/test_datasets.py
MDAnalysisData/tests/test_package_metadata.py
MDAnalysisData-0.9.0.dist-info/AUTHORS
MDAnalysisData-0.9.0.dist-info/LICENSE
MDAnalysisData-0.9.0.dist-info/METADATA
MDAnalysisData-0.9.0.dist-info/WHEEL
MDAnalysisData-0.9.0.dist-info/top_level.txt
MDAnalysisData-0.9.0.dist-info/zip-safe
MDAnalysisData-0.9.0.dist-info/RECORD
