Metadata-Version: 2.1
Name: MDAnalysisData
Version: 0.9.0
Summary: MDAnalysis example data
Home-page: https://www.mdanalysis.org
Download-URL: https://github.com/MDAnalysis/MDAnalysisData/releases
Author: Oliver Beckstein
Author-email: orbeckst@gmail.com
Maintainer: MDAnalysis Core Developers
Maintainer-email: mdanalysis@numfocus.org
License: BSD-3
Project-URL: Documentation, https://www.mdanalysis.org/MDAnalysisData
Project-URL: Developer Group, https://groups.google.com/forum/#!forum/mdnalysis-devel
Project-URL: Issue Tracker, https://github.com/mdanalysis/MDAnalysisData/issues
Project-URL: Source, https://github.com/mdanalysis/MDAnalysisData
Classifier: Development Status :: 4 - Beta
Classifier: Environment :: Console
Classifier: Intended Audience :: Science/Research
Classifier: License :: OSI Approved :: BSD License
Classifier: Operating System :: POSIX
Classifier: Operating System :: MacOS :: MacOS X
Classifier: Operating System :: Microsoft :: Windows 
Classifier: Programming Language :: Python
Classifier: Programming Language :: Python :: 3
Classifier: Programming Language :: Python :: 3.9
Classifier: Programming Language :: Python :: 3.10
Classifier: Programming Language :: Python :: 3.11
Classifier: Programming Language :: Python :: 3.12
Classifier: Topic :: Scientific/Engineering
Classifier: Topic :: Scientific/Engineering :: Bio-Informatics
Classifier: Topic :: Scientific/Engineering :: Chemistry
Classifier: Topic :: Software Development :: Libraries :: Python Modules
License-File: LICENSE
License-File: AUTHORS
Requires-Dist: tqdm
